md_redact/__init__.py
md_redact-0.2.0.dist-info/LICENSE
md_redact-0.2.0.dist-info/WHEEL
md_redact-0.2.0.dist-info/METADATA
md_redact-0.2.0.dist-info/RECORD
