Metadata-Version: 2.1
Name: md-redact
Version: 0.2.0
Summary: Redact portions of content if a condition is met
Home-page: https://github.com/willmooney3/md-redact
License: MIT
Author: Will Mooney
Author-email: will.mooney.3@gmail.com
Requires-Python: >=3.9,<4.0
Classifier: License :: OSI Approved :: MIT License
Classifier: Programming Language :: Python :: 3
Classifier: Programming Language :: Python :: 3.10
Classifier: Programming Language :: Python :: 3.9
Project-URL: Repository, https://github.com/willmooney3/md-redact
